Metadata-Version: 1.0
Name: Gauss-dist
Version: 0.1
Summary: Gaussian and Binomial distributions
Home-page: UNKNOWN
Author: Vardan Sharma
Author-email: vardans6@gmail.com
License: UNKNOWN
Platform: UNKNOWN
